bmauth/__init__.py
bmauth/auth.py
bmauth/email_providers.py
bmauth/templates/login.html
bmauth/templates/register.html
bmauth/templates/verify.html
bmauth-0.1.0.dist-info/licenses/LICENSE
bmauth-0.1.0.dist-info/METADATA
bmauth-0.1.0.dist-info/WHEEL
bmauth-0.1.0.dist-info/top_level.txt
bmauth-0.1.0.dist-info/RECORD
