Metadata-Version: 2.4
Name: bmauth
Version: 0.1.0
Summary: Biometric Authentication System for FastAPI applications
Home-page: https://github.com/samimelhem/bmauth
Author: Sami Melhem
Author-email: Sami Melhem <SaMiLMelhem23@gmail.com>
License: MIT
Project-URL: Homepage, https://github.com/samimelhem/bmauth
Project-URL: Documentation, https://github.com/samimelhem/bmauth#readme
Project-URL: Repository, https://github.com/samimelhem/bmauth
Project-URL: Bug Tracker, https://github.com/samimelhem/bmauth/issues
Keywords: authentication,biometric,fastapi,webauthn,fido2,security
Classifier: Development Status :: 3 - Alpha
Classifier: Intended Audience :: Developers
Classifier: Topic :: Software Development :: Libraries :: Python Modules
Classifier: Topic :: Security
Classifier: License :: OSI Approved :: MIT License
Classifier: Programming Language :: Python :: 3
Classifier: Programming Language :: Python :: 3.8
Classifier: Programming Language :: Python :: 3.9
Classifier: Programming Language :: Python :: 3.10
Classifier: Programming Language :: Python :: 3.11
Classifier: Framework :: FastAPI
Requires-Python: >=3.8
License-File: LICENSE
Requires-Dist: fastapi>=0.68.0
Requires-Dist: pydantic>=1.8.0
Requires-Dist: cryptography>=3.4.0
Requires-Dist: python-multipart>=0.0.5
Requires-Dist: httpx>=0.24.0
Requires-Dist: email-validator>=2.0.0
Requires-Dist: python-dotenv>=1.0.0
Provides-Extra: dev
Requires-Dist: pytest>=7.0.0; extra == "dev"
Requires-Dist: pytest-cov>=3.0.0; extra == "dev"
Requires-Dist: black>=22.0.0; extra == "dev"
Requires-Dist: flake8>=4.0.0; extra == "dev"
Requires-Dist: mypy>=0.950; extra == "dev"
Requires-Dist: twine>=6.0.0; extra == "dev"
Dynamic: author
Dynamic: home-page
Dynamic: license-file
Dynamic: requires-python
